CHANGELOG
LICENSE
MANIFEST.in
README.md
setup.py
qopen/__init__.py
qopen/core.py
qopen/imaging.py
qopen/rt.py
qopen/site.py
qopen/source.py
qopen/util.py
qopen.egg-info/PKG-INFO
qopen.egg-info/SOURCES.txt
qopen.egg-info/dependency_links.txt
qopen.egg-info/entry_points.txt
qopen.egg-info/not-zip-safe
qopen.egg-info/pbr.json
qopen.egg-info/requires.txt
qopen.egg-info/top_level.txt
qopen/example/conf.json
qopen/example/create_example_files.py
qopen/example/example_data.mseed
qopen/example/example_events.xml
qopen/example/example_inventory.xml
qopen/tests/__init__.py
qopen/tests/__main__.py
qopen/tests/test_rt.py
qopen/tests/test_site.py
qopen/tests/test_util.py
qopen/tests/test_xcore.py
qopen/tests/util.py
qopen/tests/data/usarray_dataset.json