Metadata-Version: 1.1
Name: qopen
Version: 4.3
Summary: Separation of intrinsic and scattering Q by envelope inversion
Home-page: https://github.com/trichter/qopen
Author: Tom Eulenfeld
Author-email: tom.eulenfeld@gmail.com
License: MIT
Platform: UNKNOWN
Classifier: Environment :: Console
Classifier: Intended Audience :: Science/Research
Classifier: License :: OSI Approved :: MIT License
Classifier: Operating System :: OS Independent
Classifier: Programming Language :: Python :: 3
Classifier: Programming Language :: Python :: 3.7
Classifier: Programming Language :: Python :: 3.8
Classifier: Programming Language :: Python :: 3.9
Classifier: Programming Language :: Python :: 3.10
Classifier: Topic :: Scientific/Engineering :: Physics
